MANIFEST.in
README
run_p2pool.py
setup.py
nattraverso/__init__.py
nattraverso/ipdiscover.py
nattraverso/portmapper.py
nattraverso/utils.py
nattraverso/pynupnp/__init__.py
nattraverso/pynupnp/soap.py
nattraverso/pynupnp/upnp.py
nattraverso/pynupnp/upnpxml.py
p2pool/__init__.py
p2pool/data.py
p2pool/main.py
p2pool/node.py
p2pool/p2p.py
p2pool/web.py
p2pool/work.py
p2pool/bitcoin/__init__.py
p2pool/bitcoin/data.py
p2pool/bitcoin/getwork.py
p2pool/bitcoin/height_tracker.py
p2pool/bitcoin/helper.py
p2pool/bitcoin/p2p.py
p2pool/bitcoin/script.py
p2pool/bitcoin/sha256.py
p2pool/bitcoin/stratum.py
p2pool/bitcoin/worker_interface.py
p2pool/bitcoin/networks/__init__.py
p2pool/bitcoin/networks/bitcoin.py
p2pool/bitcoin/networks/bitcoin_testnet.py
p2pool/bitcoin/networks/btcregtest.py
p2pool/bitcoin/networks/fastcoin.py
p2pool/bitcoin/networks/litecoin.py
p2pool/bitcoin/networks/litecoin_testnet.py
p2pool/bitcoin/networks/namecoin.py
p2pool/bitcoin/networks/namecoin_testnet.py
p2pool/bitcoin/networks/terracoin.py
p2pool/bitcoin/networks/terracoin_testnet.py
p2pool/bitcoin/networks/vertcoin.py
p2pool/bitcoin/networks/vertcoin_testnet.py
p2pool/networks/__init__.py
p2pool/networks/bitcoin.py
p2pool/networks/bitcoin_testnet.py
p2pool/networks/btcregtest.py
p2pool/networks/fastcoin.py
p2pool/networks/litecoin.py
p2pool/networks/litecoin_testnet.py
p2pool/networks/terracoin.py
p2pool/networks/terracoin_testnet.py
p2pool/networks/vertcoin.py
p2pool/networks/vertcoin_testnet.py
p2pool/util/__init__.py
p2pool/util/datachunker.py
p2pool/util/deferral.py
p2pool/util/deferred_resource.py
p2pool/util/expiring_dict.py
p2pool/util/fixargparse.py
p2pool/util/forest.py
p2pool/util/graph.py
p2pool/util/jsonrpc.py
p2pool/util/logging.py
p2pool/util/math.py
p2pool/util/memoize.py
p2pool/util/memory.py
p2pool/util/p2protocol.py
p2pool/util/pack.py
p2pool/util/segwit_addr.py
p2pool/util/skiplist.py
p2pool/util/switchprotocol.py
p2pool/util/variable.py
p2pool_vtc.egg-info/PKG-INFO
p2pool_vtc.egg-info/SOURCES.txt
p2pool_vtc.egg-info/dependency_links.txt
p2pool_vtc.egg-info/not-zip-safe
p2pool_vtc.egg-info/requires.txt
p2pool_vtc.egg-info/top_level.txt
web-static/d3.v2.min.js
web-static/favicon.ico
