Metadata-Version: 1.0
Name: p2pool-vtc
Version: 3.0.0
Summary: p2pool for Vertcoin
Home-page: http://github.com/vertcoin-project/p2pool-vtc
Author: James Lovejoy
Author-email: jameslovejoy1@gmail.com
License: GPLv3
Platform: UNKNOWN
